huoutil/__init__.py
huoutil/cache.py
huoutil/seq.py
huoutil/uni.py
huoutil/util.py
huoutil-1.3.3.dist-info/LICENSE
huoutil-1.3.3.dist-info/METADATA
huoutil-1.3.3.dist-info/WHEEL
huoutil-1.3.3.dist-info/top_level.txt
huoutil-1.3.3.dist-info/RECORD
