Metadata-Version: 2.1
Name: huoutil
Version: 1.3.3
Summary: util module of Huarong Huo
Home-page: UNKNOWN
Author: Huarong Huo
Author-email: huohuarong@gmail.com
License: UNKNOWN
Platform: UNKNOWN
License-File: LICENSE
Requires-Dist: six
